{"menus":[{"section":"Modules","items":[{"title":"Testimonial","icon":"fas fa-users","url":"\/admin\/testimonial"},{"title":"Partners","icon":"fas fa-user","url":"\/admin\/partner"},{"title":"Video","icon":"fas fa-video","url":"\/admin\/video"},{"title":"FAQs","icon":"fas fa-align-justify","url":"\/admin\/faq"},{"title":"Dealers","icon":"fas fa-align-justify","url":"\/admin\/dealer"},{"title":"Company","icon":"fas fa-align-justify","url":"\/admin\/service"},{"title":"File Management","icon":"fas fa-file-pdf","url":"\/admin\/file-management"},{"title":"Motor Options","icon":"fab fa-monero","url":"\/admin\/motoroption"},{"title":"Size","icon":"fas fa-won-sign","url":"\/admin\/size"},{"title":"Dealer Account","icon":"fas fa-user","url":"\/admin\/dealer-account"}]}]}